mangainfo/__init__.py
mangainfo/__main__.py
mangainfo/_core.py
mangainfo/_models.py
mangainfo/_utils.py
mangainfo/_version.py
mangainfo/py.typed
mangainfo-0.1.1.dist-info/METADATA
mangainfo-0.1.1.dist-info/WHEEL
mangainfo-0.1.1.dist-info/entry_points.txt
mangainfo-0.1.1.dist-info/RECORD
