Metadata-Version: 2.1
Name: mangainfo
Version: 0.1.1
Summary: Libary and a CLI tool to generate mediainfo for manga archives
Home-page: https://ravencentric.github.io/mangainfo
License: Unlicense
Author: Raventric
Author-email: 78981416+Ravencentric@users.noreply.github.com
Requires-Python: >=3.9
Classifier: License :: OSI Approved
Classifier: License :: OSI Approved :: The Unlicense (Unlicense)
Classifier: Operating System :: OS Independent
Classifier: Programming Language :: Python :: 3
Classifier: Programming Language :: Python :: 3.9
Classifier: Programming Language :: Python :: 3.10
Classifier: Programming Language :: Python :: 3.11
Classifier: Programming Language :: Python :: 3.12
Classifier: Typing :: Typed
Requires-Dist: archivefile (>=0.3.1)
Requires-Dist: importlib-metadata (>=7.1.0) ; python_version < "3.10"
Requires-Dist: pydantic (>=2.7.1)
Requires-Dist: pymediainfo (>=6.1.0)
Requires-Dist: typing-extensions (>=4.11.0)
Project-URL: Documentation, https://ravencentric.github.io/mangainfo
Project-URL: Repository, https://github.com/Ravencentric/mangainfo
